Metadata-Version: 2.1
Name: price-product-scraper
Version: 1.0.0
Summary: A python library to scrape product data on price automatically.
Home-page: https://datakund.com
Author: DataKund
Author-email: datakund@gmail.com
License: Apache License 2.0
Keywords: price python bot_studio scraper data product info web-scraping
Platform: UNKNOWN
